multibutton_debouncer.py
multibutton_debouncer-0.0.1.dist-info/LICENSE
multibutton_debouncer-0.0.1.dist-info/METADATA
multibutton_debouncer-0.0.1.dist-info/WHEEL
multibutton_debouncer-0.0.1.dist-info/top_level.txt
multibutton_debouncer-0.0.1.dist-info/RECORD
