Metadata-Version: 2.1
Name: multibutton-debouncer
Version: 0.0.1
Summary: Debouncer supporting multi-button and multi-press gestures.
Author-email: David Hand <davidhand@davidhand.com>
License: MIT
Project-URL: Homepage, https://github.com/ptolemarch/multibutton-debouncer
Project-URL: Bug Tracker, https://github.com/ptolemarch/multibutton-debouncer/issues
Keywords: adafruit,blinka,circuitpython,micropython,debouncer,debounce,multi,multibutton
Classifier: Intended Audience :: Developers
Classifier: Topic :: Software Development :: Libraries
Classifier: Topic :: Software Development :: Embedded Systems
Classifier: Topic :: System :: Hardware
Classifier: Programming Language :: Python :: 3
Classifier: License :: OSI Approved :: MIT License
Classifier: Operating System :: OS Independent
Requires-Python: >=3.7
License-File: LICENSE
Requires-Dist: adafruit-circuitpython-debouncer
Requires-Dist: Adafruit-Blinka
